pyterrier_services/__init__.py
pyterrier_services/core.py
pyterrier_services/dblp.py
pyterrier_services/google.py
pyterrier_services/pinecone.py
pyterrier_services/semantic_scholar.py
pyterrier_services/pt_docs/dblp.rst
pyterrier_services/pt_docs/google.rst
pyterrier_services/pt_docs/index.rst
pyterrier_services/pt_docs/pinecone.rst
pyterrier_services/pt_docs/semantic-scholar.rst
pyterrier_services-0.4.5.dist-info/licenses/LICENSE
pyterrier_services-0.4.5.dist-info/METADATA
pyterrier_services-0.4.5.dist-info/WHEEL
pyterrier_services-0.4.5.dist-info/top_level.txt
pyterrier_services-0.4.5.dist-info/RECORD
