Metadata-Version: 2.4
Name: pyterrier-services
Version: 0.4.5
Summary: PyTerrier components for API Services
Author-email: Sean MacAvaney <sean.macavaney@glasgow.ac.uk>
Maintainer-email: Sean MacAvaney <sean.macavaney@glasgow.ac.uk>
Project-URL: Repository, https://github.com/seanmacavaney/pyterrier-services
Project-URL: Bug Tracker, https://github.com/seanmacavaney/pyterrier-services/issues
Classifier: Programming Language :: Python
Classifier: Operating System :: OS Independent
Classifier: Topic :: Text Processing
Classifier: Topic :: Text Processing :: Indexing
Classifier: License :: OSI Approved :: MIT License
Requires-Python: >=3.6
License-File: LICENSE
Requires-Dist: python-terrier
Requires-Dist: pyterrier-alpha
Requires-Dist: requests
Dynamic: license-file
